LICENSE.txt
MANIFEST.in
README.rst
setup.py
tox.ini
drift_api/__init__.py
drift_api.egg-info/PKG-INFO
drift_api.egg-info/SOURCES.txt
drift_api.egg-info/dependency_links.txt
drift_api.egg-info/requires.txt
drift_api.egg-info/top_level.txt