Metadata-Version: 1.1
Name: drift-api
Version: 0.1.0
Summary: A wrapper for the Drift API
Home-page: https://github.com/15five/drift-api
Author: Paul Logston
Author-email: paul@15five.com
License: MIT
Download-URL: https://github.com/15five/drift-api/archive/master.zip
Keywords: drift http api
Platform: UNKNOWN
Classifier: Development Status :: 4 - Beta
Classifier: Environment :: Web Environment
Classifier: Intended Audience :: Developers
Classifier: License :: OSI Approved :: MIT License
Classifier: Natural Language :: English
Classifier: Operating System :: OS Independent
Classifier: Programming Language :: Python :: 2.7
Classifier: Programming Language :: Python :: 3.3
Classifier: Programming Language :: Python :: 3.4
Classifier: Programming Language :: Python :: 3.5
Classifier: Programming Language :: Python :: 3.6
Classifier: Topic :: Internet
Classifier: Topic :: Software Development :: Libraries :: Python Modules
